kompira_common/__init__.py
kompira_common/config.py
kompira_common/config_argparse.py
kompira_common/connector.py
kompira_common/daemon_ctrl.py
kompira_common/job_message.py
kompira_common/qname.py
kompira_common/setup_logger.py
kompira_common/utils.py
kompira_common/version.py
kompira_sendevt/__init__.py
kompira_sendevt/kompira_sendevt.py
Kompira_sendevt-2.0.0.dist-info/METADATA
Kompira_sendevt-2.0.0.dist-info/WHEEL
Kompira_sendevt-2.0.0.dist-info/entry_points.txt
Kompira_sendevt-2.0.0.dist-info/top_level.txt
Kompira_sendevt-2.0.0.dist-info/RECORD
