Metadata-Version: 2.1
Name: Kompira_sendevt
Version: 2.0.0
Summary: UNKNOWN
License: UNKNOWN
Platform: UNKNOWN
Requires-Dist: amqpstorm ~=2.10.6
Requires-Dist: packaging ~=24.0
